deke/__init__.py
deke/api.py
deke/app.py
deke/deke.py
deke-0.3.1.dist-info/DESCRIPTION.rst
deke-0.3.1.dist-info/METADATA
deke-0.3.1.dist-info/RECORD
deke-0.3.1.dist-info/WHEEL
deke-0.3.1.dist-info/entry_points.txt
deke-0.3.1.dist-info/metadata.json
deke-0.3.1.dist-info/top_level.txt
