Metadata-Version: 2.0
Name: deke
Version: 0.3.1
Summary: A convenient HockeyApp API package making it easier than ever to manage apps, gather specific app statistics, and download builds.
Home-page: https://github.com/misternate/deke
Author: Nate Edwards
Author-email: nathan.d.edwards@gmail.com
License: UNKNOWN
Keywords: hockeyapp app center distribution ci
Platform: UNKNOWN
Classifier: Development Status :: 4 - Beta
Classifier: Intended Audience :: Developers
Classifier: Topic :: Software Development :: Build Tools
Classifier: License :: OSI Approved :: MIT License
Classifier: Programming Language :: Python :: 2.7
Classifier: Programming Language :: Python :: 3
Classifier: Programming Language :: Python :: 3.4
Classifier: Programming Language :: Python :: 3.5
Classifier: Programming Language :: Python :: 3.6
Requires-Dist: requests
Requires-Dist: tqdm
